timeblock/__init__.py
timeblock/block.py
timeblock/tests/test_blocktimer.py
timeblock-0.1.1.dist-info/METADATA
timeblock-0.1.1.dist-info/WHEEL
timeblock-0.1.1.dist-info/top_level.txt
timeblock-0.1.1.dist-info/RECORD
