Metadata-Version: 2.1
Name: timeblock
Version: 0.1.1
Summary: Time blocks of code using a context manager
Author-email: Daniel Hails <timeblock@hails.info>
Project-URL: Homepage, https://github.com/DJRHails/timeblock
Project-URL: Bug Tracker, https://github.com/DJRHails/timeblock/issues
Requires-Python: >=3.10
